<?xml version="1.0" encoding="utf-8" standalone="yes"?>
<languages>
	<language name="English" id="en">
		<displaychannels>
			<displaychannel name="mobile">
				<name>Mobile</name>
			</displaychannel>
			<displaychannel name="web">
				<name>Web</name>
			</displaychannel>
		</displaychannels>
		<displayoptions>
			<screen>Screen Width</screen>
			<full>Full (1/1)</full>
			<threequarter>Three quarters width (3/4)</threequarter>
			<half>Half (1/2)</half>
			<narrow>Narrow (1/3)</narrow>
			<wide>Wide (2/3)</wide>
			<one-quarter>One Quarter (1/4)</one-quarter>
			<one-sixth>One Sixth Width (1/6)</one-sixth>
		
	</displayoptions>
		<resolutions>
			<standard>Standard (1366x768)</standard>
			<ipadhorizontal>iPad horizontal (1024x768)</ipadhorizontal>
			<iphonevertical>iPhone vertical (320x568)</iphonevertical>
			<androidvertical>Android vertical (480x800)</androidvertical>
			<iphone11>iPhone 11 (414x896)</iphone11>
			<ipadair>iPad Air (768x1024)</ipadair>
		</resolutions>
	</language>
</languages>